{
  "peers": [
    {
      "discovery_host": "0b1b632089934e2db2a2cdd6fb13a266-vp1.dev.blockchain.ibm.com",
      "discovery_port": 30303,
      "api_host": "0b1b632089934e2db2a2cdd6fb13a266-vp1.dev.blockchain.ibm.com",
      "api_port_tls": 443,
      "api_port": 443,
      "type": "peer",
      "network_id": "0b1b632089934e2db2a2cdd6fb13a266",
      "container_id": "f2c043e24f312253c3fb4c0d48018e67948f8b4ef4c6163240e1a5fe57aee355",
      "id": "0b1b632089934e2db2a2cdd6fb13a266-vp1",
      "api_url": "http://0b1b632089934e2db2a2cdd6fb13a266-vp1.dev.blockchain.ibm.com:443"
    },
    {
      "discovery_host": "0b1b632089934e2db2a2cdd6fb13a266-vp3.dev.blockchain.ibm.com",
      "discovery_port": 30303,
      "api_host": "0b1b632089934e2db2a2cdd6fb13a266-vp3.dev.blockchain.ibm.com",
      "api_port_tls": 443,
      "api_port": 443,
      "type": "peer",
      "network_id": "0b1b632089934e2db2a2cdd6fb13a266",
      "container_id": "9ec6bd5ea0147c6fe9ca634b1bac6245ec02af355bc4566fb7a14a49e1478134",
      "id": "0b1b632089934e2db2a2cdd6fb13a266-vp3",
      "api_url": "http://0b1b632089934e2db2a2cdd6fb13a266-vp3.dev.blockchain.ibm.com:443"
    },
    {
      "discovery_host": "0b1b632089934e2db2a2cdd6fb13a266-vp2.dev.blockchain.ibm.com",
      "discovery_port": 30303,
      "api_host": "0b1b632089934e2db2a2cdd6fb13a266-vp2.dev.blockchain.ibm.com",
      "api_port_tls": 443,
      "api_port": 443,
      "type": "peer",
      "network_id": "0b1b632089934e2db2a2cdd6fb13a266",
      "container_id": "b6cf409a0fb1b003c45fe1cd4c79ca21b88546f0546b57557f9af06c8014a156",
      "id": "0b1b632089934e2db2a2cdd6fb13a266-vp2",
      "api_url": "http://0b1b632089934e2db2a2cdd6fb13a266-vp2.dev.blockchain.ibm.com:443"
    },
    {
      "discovery_host": "0b1b632089934e2db2a2cdd6fb13a266-vp0.dev.blockchain.ibm.com",
      "discovery_port": 30303,
      "api_host": "0b1b632089934e2db2a2cdd6fb13a266-vp0.dev.blockchain.ibm.com",
      "api_port_tls": 443,
      "api_port": 443,
      "type": "peer",
      "network_id": "0b1b632089934e2db2a2cdd6fb13a266",
      "container_id": "73758afee9554c14c8b3924eab4f481a80e14456fa0cdd34df739ac3c1083706",
      "id": "0b1b632089934e2db2a2cdd6fb13a266-vp0",
      "api_url": "http://0b1b632089934e2db2a2cdd6fb13a266-vp0.dev.blockchain.ibm.com:443"
    }
  ],
  "ca": {
    "0b1b632089934e2db2a2cdd6fb13a266-ca": {
      "url": "0b1b632089934e2db2a2cdd6fb13a266-ca.dev.blockchain.ibm.com:30303",
      "discovery_host": "0b1b632089934e2db2a2cdd6fb13a266-ca.dev.blockchain.ibm.com",
      "discovery_port": 30303,
      "api_host": "0b1b632089934e2db2a2cdd6fb13a266-ca.dev.blockchain.ibm.com",
      "api_port_tls": 30303,
      "api_port": 30303,
      "type": "ca",
      "network_id": "0b1b632089934e2db2a2cdd6fb13a266",
      "container_id": "c567596a883df61a5cbcd7b7a71da10d485861bba2bee15afe2f2dde10166753"
    }
  },
  "users": [
    {
      "enrollId": "admin",
      "enrollSecret": "03a1078c9d",
      "group": "group1",
      "affiliation": "0001"
    },
    {
      "enrollId": "WebAppAdmin",
      "enrollSecret": "ab52dffdbf",
      "group": "group1",
      "affiliation": "0001"
    },
    {
      "enrollId": "user_type1_0",
      "enrollSecret": "3b966eab79",
      "group": "group1",
      "affiliation": "0001"
    },
    {
      "enrollId": "user_type1_1",
      "enrollSecret": "e743fd0e0a",
      "group": "group1",
      "affiliation": "0001"
    },
    {
      "enrollId": "user_type1_2",
      "enrollSecret": "1c2978c29c",
      "group": "group1",
      "affiliation": "0001"
    },
    {
      "enrollId": "user_type1_3",
      "enrollSecret": "5eb5727894",
      "group": "group1",
      "affiliation": "0001"
    },
    {
      "enrollId": "user_type1_4",
      "enrollSecret": "94a35eb27e",
      "group": "group1",
      "affiliation": "0001"
    },
    {
      "enrollId": "user_type2_0",
      "enrollSecret": "ddc53c0d2a",
      "group": "group1",
      "affiliation": "0001"
    },
    {
      "enrollId": "user_type2_1",
      "enrollSecret": "261ab0c1b8",
      "group": "group1",
      "affiliation": "0001"
    },
    {
      "enrollId": "user_type2_2",
      "enrollSecret": "69cd2619eb",
      "group": "group1",
      "affiliation": "0001"
    },
    {
      "enrollId": "user_type2_3",
      "enrollSecret": "a9666a5566",
      "group": "group1",
      "affiliation": "0001"
    },
    {
      "enrollId": "user_type2_4",
      "enrollSecret": "b1ba1dad51",
      "group": "group1",
      "affiliation": "0001"
    },
    {
      "enrollId": "user_type4_0",
      "enrollSecret": "96dd01d8a6",
      "group": "group1",
      "affiliation": "0001"
    },
    {
      "enrollId": "user_type4_1",
      "enrollSecret": "fd33e7e659",
      "group": "group1",
      "affiliation": "0001"
    },
    {
      "enrollId": "user_type4_2",
      "enrollSecret": "46c2ca5a50",
      "group": "group1",
      "affiliation": "0001"
    },
    {
      "enrollId": "user_type4_3",
      "enrollSecret": "8c8a2339d6",
      "group": "group1",
      "affiliation": "0001"
    },
    {
      "enrollId": "user_type4_4",
      "enrollSecret": "7b69c1a792",
      "group": "group1",
      "affiliation": "0001"
    },
    {
      "enrollId": "user_type8_0",
      "enrollSecret": "e090baf6e1",
      "group": "group1",
      "affiliation": "0001"
    },
    {
      "enrollId": "user_type8_1",
      "enrollSecret": "e87d801213",
      "group": "group1",
      "affiliation": "0001"
    },
    {
      "enrollId": "user_type8_2",
      "enrollSecret": "824df30cc0",
      "group": "group1",
      "affiliation": "0001"
    },
    {
      "enrollId": "user_type8_3",
      "enrollSecret": "1fad821ced",
      "group": "group1",
      "affiliation": "0001"
    },
    {
      "enrollId": "user_type8_4",
      "enrollSecret": "e668f53f4c",
      "group": "group1",
      "affiliation": "0001"
    }
  ]
}

